{"id": 2851, "qid": 2851, "publicid": 2851, "orgid": 0, "levelname": "4D", "min_levelname": "", "max_levelname": "", "qtype": 1, "qtypename": "\u6b7b\u6d3b\u9898", "status": 2, "userid": 1, "username": "admin", "hasdia": true, "dias": [], "attr_type": 0, "layoutnumber": 1, "issingle": true, "enable_answer": true, "sms_count": 0, "edit_count": 1, "islei": false, "taotaiid": 0, "bookinfos": [{"bookname": "\u5bb6\u6559\u7f51\u7684\u6b7b\u6d3b\u9898", "bookid": 113, "pinyin": "", "nodename": "\u6839\u76ee\u5f55", "bookurl": 113}, {"bookname": "\u9673\u7956\u5fb7 \u6b7b\u6d3b\u5927\u5168", "bookid": 210, "pinyin": "chenzhude", "nodename": "\u4fee\u6b63", "bookurl": "chenzhude"}, {"bookname": "\u85e4\u6cfd\u79c0\u884c01\u6770\u4f5c\u96c6", "bookid": 28495, "pinyin": "", "nodename": "\u9ad8\u7ea7\u8005\u90e8", "bookurl": 28495}, {"bookname": "\u8bd8\u68cb\u540d\u5bb6\u4e13\u8457", "bookid": 201, "pinyin": "qiantian", "nodename": "\u85e4\u6cfd\u79c0\u884c \u56f4\u68cb\u6b7b\u6d3b\u6770\u4f5c\u96c6", "bookurl": "qiantian"}, {"bookname": "\u6c64\u59c6\u9ad8\u7ea7\u6b7b\u6d3b", "bookid": 213, "pinyin": "tom", "nodename": "\u9ad8\u7ea7 1-200 \u7f3a9", "bookurl": "tom"}, {"bookname": "\u56f4\u68cb\u6b7b\u6d3b\u5927\u5168", "bookid": 42, "pinyin": "daquan", "nodename": "TOM\u7f51\u6b7b\u6d3b\u9898\u9ad8\u7ea7", "bookurl": "daquan"}, {"bookname": "\u5176\u4ed6\u65e5\u672c\u8a70\u68cb\u540d\u5bb6\u7684\u4f20\u4e16\u7cbe\u54c1", "bookid": 205, "pinyin": "qita", "nodename": "\u85e4\u6cfd\u79c0\u884c \u6770\u4f5c\u96c6", "bookurl": "qita"}, {"bookname": "\u56f4\u68cb\u5929\u57305\u6bb5\u9898", "bookid": 219, "pinyin": "", "nodename": "\u8ba1\u7b97\u4e0e\u611f\u89c95D", "bookurl": 219}], "specs": [], "taskresult": {"ok_nums": [2, 0, 1, 0, 19, 0, 1, 1, 4, 0, 1, 3, 2, 5, 5, 3, 8, 1, 7, 7, 14, 35, 27, 69, 98, 98, 180, 129, 146, 100], "fail_nums": [39, 23, 32, 25, 50, 21, 27, 24, 37, 34, 33, 41, 42, 42, 41, 29, 30, 39, 47, 49, 66, 201, 89, 112, 92, 98, 82, 29, 25, 18], "ok_total": 966, "fail_total": 1517}, "xuandians": [], "xds": [], "options": [], "vote": 4.9, "name": "", "title": "\u85e4\u6cfd\u79c0\u884c\u4e5d\u6bb5\u521b\u4f5c", "c": "amsTVl0QHRATVkMQHRATV0MQHRATV0AQHRATVEEQHRATVF0QHRATUFwQHRATUF8QHRATVlwQbBwRaRBQXhIdEhBRQRIdEhBRQBIdEhBRQxIdEhBUQxIdEhBVQxIdEhBaQBJsbw==", "r": 1, "prepos": [["od", "qd", "qe", "re", "sf"], ["ob", "pc", "qc"]], "xv": 2, "points": [], "lu": 19, "blackfirst": true, "is_share": true, "answers": [{"id": 4159, "st": 2, "ty": 1, "nu": 1, "username": "admin", "userid": 1, "pts": [{"p": "sc", "c": "\u6258\uff0c\u53ea\u6b64\u4e00\u624b\uff01\u5176\u4ed6\u7740\u6cd5\uff0c\u767d\u53efa\u4f4d\u5148\u5c16\u6d3b\u68cb\u3002"}, {"p": "sd", "c": ""}, {"p": "rd", "c": ""}, {"p": "rb", "c": ""}, {"p": "qa", "c": "\u8981\u70b9\uff01"}, {"p": "pa", "c": ""}, {"p": "na", "c": ""}, {"p": "qb", "c": ""}, {"p": "oa", "c": ""}, {"p": "ra", "c": ""}, {"p": "oc", "c": ""}, {"p": "sb", "c": "\u4e0d\u6127\u662f\u9ad8\u624b\uff01PF\uff0cPF"}, {"p": "pb", "c": ""}], "v": 0, "ok_count": 16, "change_count": 0, "bad_count": 0, "error_count": 0, "created": 0}, {"id": 4160, "st": 2, "ty": 2, "nu": 2, "username": "admin", "userid": 1, "pts": [{"p": "sc", "c": "\u6258\uff0c\u53ea\u6b64\u4e00\u624b\uff01\u5176\u4ed6\u7740\u6cd5\uff0c\u767d\u53efa\u4f4d\u5148\u5c16\u6d3b\u68cb\u3002"}, {"p": "sd", "c": ""}, {"p": "rd", "c": ""}, {"p": "sb", "c": ""}, {"p": "ra", "c": ""}, {"p": "oa", "c": ""}, {"p": "qb", "c": ""}, {"p": "oc", "c": ""}, {"p": "pa", "c": ""}, {"p": "pb", "c": ""}, {"p": "qa", "c": "\u767d\u68cb\u88ab\u805a\u6740\uff01"}], "v": 0, "ok_count": 10, "change_count": 15, "bad_count": 0, "error_count": 0, "created": 0}, {"id": 4161, "st": 2, "ty": 2, "nu": 3, "username": "admin", "userid": 1, "pts": [{"p": "sc", "c": "\u6258\uff0c\u53ea\u6b64\u4e00\u624b\uff01\u5176\u4ed6\u7740\u6cd5\uff0c\u767d\u53efa\u4f4d\u5148\u5c16\u6d3b\u68cb\u3002"}, {"p": "sd", "c": ""}, {"p": "rd", "c": ""}, {"p": "sb", "c": ""}, {"p": "ra", "c": ""}, {"p": "qb", "c": ""}, {"p": "oc", "c": ""}, {"p": "na", "c": ""}, {"p": "ma", "c": ""}, {"p": "pa", "c": "\u7f13\u6c14\u52ab\uff0c\u5931\u8d25\uff01"}], "v": 0, "ok_count": 1, "change_count": 11, "bad_count": 0, "error_count": 0, "created": 0}, {"id": 4162, "st": 2, "ty": 3, "nu": 4, "username": "admin", "userid": 1, "pts": [{"p": "qb", "c": "\u4e0d\u662f\u6740\u68cb\u7684\u5730\u65b9"}, {"p": "sd", "c": ""}, {"p": "rd", "c": ""}, {"p": "rb", "c": ""}, {"p": "ra", "c": ""}, {"p": "pa", "c": ""}, {"p": "qa", "c": ""}, {"p": "sc", "c": "\u767d\u7c98\u662f\u5148\u624b\uff0c\u5df2\u6210\u6d3b\u68cb\u3002\u518d\u8bd5\u8bd5\uff01"}], "v": 0, "ok_count": 0, "change_count": 0, "bad_count": 0, "error_count": 0, "created": 0}, {"id": 163249, "st": 2, "ty": 2, "nu": 5, "username": "\u7231\u4e50\u5955", "userid": 2768, "pts": [{"p": "sc", "c": ""}, {"p": "sd", "c": ""}, {"p": "rd", "c": ""}, {"p": "sb", "c": ""}, {"p": "ra", "c": ""}, {"p": "pa", "c": ""}, {"p": "oc", "c": ""}, {"p": "qb", "c": ""}, {"p": "na", "c": "\u6b63\u89e33"}], "v": 0, "ok_count": 0, "change_count": 10, "bad_count": 0, "error_count": 0, "created": 1390801225}, {"id": 189236, "st": 2, "ty": 2, "nu": 6, "username": "\u7231\u4e50\u5955", "userid": 2768, "pts": [{"p": "sc", "c": ""}, {"p": "sd", "c": ""}, {"p": "rd", "c": ""}, {"p": "sb", "c": ""}, {"p": "ra", "c": ""}, {"p": "oa", "c": ""}, {"p": "qb", "c": ""}, {"p": "oc", "c": ""}, {"p": "pa", "c": "\u6b63\u89e32"}], "v": 0, "ok_count": 0, "change_count": 10, "bad_count": 0, "error_count": 0, "created": 1407127132}, {"id": 189237, "st": 2, "ty": 2, "nu": 7, "username": "\u7231\u4e50\u5955", "userid": 2768, "pts": [{"p": "sc", "c": ""}, {"p": "sd", "c": ""}, {"p": "rd", "c": ""}, {"p": "sb", "c": ""}, {"p": "ra", "c": ""}, {"p": "pa", "c": ""}, {"p": "oc", "c": ""}, {"p": "na", "c": ""}, {"p": "qb", "c": "\u6b63\u89e34"}], "v": 0, "ok_count": 0, "change_count": 10, "bad_count": 0, "error_count": 0, "created": 1407127132}, {"id": 419931, "st": 2, "ty": 3, "nu": 8, "username": "kenny", "userid": 23199, "pts": [{"p": "sc", "c": ""}, {"p": "sd", "c": ""}, {"p": "rd", "c": ""}, {"p": "rb", "c": ""}, {"p": "qa", "c": ""}, {"p": "pa", "c": ""}, {"p": "oc", "c": ""}, {"p": "ra", "c": ""}], "v": 0, "ok_count": 0, "change_count": 0, "bad_count": 10, "error_count": 0, "created": 1474688772}, {"id": 542185, "st": 2, "ty": 1, "nu": 9, "username": "\u6c5f\u6c49\u601d\u5f52\u5ba2", "userid": 6563, "pts": [{"p": "sc", "c": ""}, {"p": "sd", "c": ""}, {"p": "rd", "c": ""}, {"p": "rb", "c": ""}, {"p": "qa", "c": ""}, {"p": "pa", "c": ""}, {"p": "na", "c": ""}, {"p": "qb", "c": ""}, {"p": "oc", "c": ""}, {"p": "ra", "c": ""}, {"p": "oa", "c": ""}, {"p": "sb", "c": ""}, {"p": "pb", "c": ""}], "v": 0, "ok_count": 53, "change_count": 0, "bad_count": 0, "error_count": 0, "created": 1509323292}, {"id": 610806, "st": 2, "ty": 1, "nu": 10, "username": "\u738b\u5c0f\u6708", "userid": 143146, "pts": [{"p": "sc", "c": ""}, {"p": "sd", "c": ""}, {"p": "rd", "c": ""}, {"p": "rb", "c": ""}, {"p": "qa", "c": ""}, {"p": "pa", "c": ""}, {"p": "na", "c": ""}, {"p": "ra", "c": ""}, {"p": "oa", "c": ""}, {"p": "qb", "c": ""}, {"p": "oc", "c": ""}, {"p": "sb", "c": ""}, {"p": "pb", "c": ""}], "v": 0, "ok_count": 52, "change_count": 0, "bad_count": 0, "error_count": 0, "created": 1522727165}, {"id": 688470, "st": 2, "ty": 3, "nu": 12, "username": "kenny", "userid": 23199, "pts": [{"p": "sc", "c": ""}, {"p": "sd", "c": ""}, {"p": "rd", "c": ""}, {"p": "rb", "c": ""}, {"p": "oa", "c": ""}, {"p": "pa", "c": ""}, {"p": "qa", "c": ""}, {"p": "na", "c": ""}, {"p": "ma", "c": ""}, {"p": "ra", "c": ""}, {"p": "oa", "c": ""}, {"p": "qb", "c": ""}, {"p": "oc", "c": "\u4e24\u624b\u52ab\uff0c\u5931\u8d25"}], "v": 0, "ok_count": 0, "change_count": 0, "bad_count": 50, "error_count": 0, "created": 1538230816}, {"id": 1040652, "st": 2, "ty": 3, "nu": 13, "username": "\u6211\u53eb\u5c0fQ", "userid": 54120, "pts": [{"p": "sc", "c": ""}, {"p": "sd", "c": ""}, {"p": "rd", "c": ""}, {"p": "rb", "c": ""}, {"p": "pa", "c": ""}, {"p": "qa", "c": ""}], "v": 0, "ok_count": 1, "change_count": 0, "bad_count": 10, "error_count": 0, "created": 1583557847}, {"id": 1473140, "st": 2, "ty": 2, "nu": 14, "username": "\u6211\u662f\u5929\u624d\u54e6", "userid": 753536, "pts": [{"p": "sc", "c": ""}, {"p": "sb", "c": ""}, {"p": "ra", "c": ""}, {"p": "qb", "c": ""}, {"p": "oc", "c": ""}, {"p": "pa", "c": ""}, {"p": "na", "c": ""}], "v": 0, "ok_count": 1, "change_count": 50, "bad_count": 0, "error_count": 0, "created": 1625553350}, {"id": 2186626, "st": 1, "ty": 2, "nu": 16, "username": "jfangsteve", "userid": 1074375, "pts": [{"p": "sc", "c": ""}, {"p": "sb", "c": ""}, {"p": "ra", "c": ""}, {"p": "oc", "c": ""}, {"p": "pa", "c": ""}, {"p": "oa", "c": ""}, {"p": "qb", "c": ""}, {"p": "sd", "c": ""}, {"p": "rd", "c": ""}], "v": 0, "ok_count": 0, "change_count": 1, "bad_count": 0, "error_count": 0, "created": 1693869099}, {"id": 2263369, "st": 1, "ty": 1, "nu": 17, "username": "\u6298\u817e\u7fa4\u6768\u70ab", "userid": 663436, "pts": [{"p": "sc", "c": ""}, {"p": "sd", "c": ""}, {"p": "rd", "c": ""}, {"p": "rb", "c": ""}, {"p": "qa", "c": ""}, {"p": "pa", "c": ""}, {"p": "na", "c": ""}, {"p": "qb", "c": ""}, {"p": "oa", "c": ""}, {"p": "oc", "c": ""}, {"p": "pb", "c": ""}], "v": 0, "ok_count": 1, "change_count": 0, "bad_count": 0, "error_count": 0, "created": 1704720361}, {"id": 2429967, "st": 1, "ty": 1, "nu": 18, "username": "wx_43899135194727", "userid": 1850898, "pts": [{"p": "sc", "c": ""}, {"p": "rb", "c": ""}, {"p": "qa", "c": ""}, {"p": "pa", "c": ""}, {"p": "na", "c": ""}, {"p": "ra", "c": ""}, {"p": "oa", "c": ""}, {"p": "qb", "c": ""}, {"p": "oc", "c": ""}, {"p": "sb", "c": ""}, {"p": "pb", "c": ""}, {"p": "rd", "c": ""}, {"p": "sd", "c": ""}, {"p": "ob", "c": ""}, {"p": "lh", "c": ""}, {"p": "li", "c": ""}, {"p": "pb", "c": ""}, {"p": "se", "c": ""}, {"p": "sd", "c": ""}, {"p": "ob", "c": ""}, {"p": "mi", "c": ""}, {"p": "mj", "c": ""}, {"p": "pb", "c": ""}, {"p": "sg", "c": ""}, {"p": "se", "c": ""}, {"p": "ob", "c": ""}], "v": 0, "ok_count": 1, "change_count": 0, "bad_count": 0, "error_count": 0, "created": 1723473644}, {"id": 2526099, "st": 1, "ty": 1, "nu": 19, "username": "Albert.Chen", "userid": 1494560, "pts": [{"p": "sc", "c": ""}, {"p": "rb", "c": ""}, {"p": "qa", "c": ""}, {"p": "pa", "c": ""}, {"p": "na", "c": ""}, {"p": "ra", "c": ""}, {"p": "oa", "c": ""}, {"p": "qb", "c": ""}, {"p": "oc", "c": ""}, {"p": "sb", "c": ""}, {"p": "pb", "c": ""}, {"p": "sd", "c": ""}, {"p": "rd", "c": ""}, {"p": "ob", "c": ""}], "v": 0, "ok_count": 1, "change_count": 0, "bad_count": 0, "error_count": 0, "created": 1733558068}, {"id": 2595041, "st": 1, "ty": 2, "nu": 20, "username": "wx_221143784194019", "userid": 2233013, "pts": [{"p": "sc", "c": ""}, {"p": "sd", "c": ""}, {"p": "rd", "c": ""}, {"p": "rb", "c": ""}, {"p": "qa", "c": ""}, {"p": "pa", "c": ""}, {"p": "na", "c": ""}, {"p": "oc", "c": ""}, {"p": "oa", "c": ""}, {"p": "qb", "c": ""}, {"p": "pb", "c": ""}], "v": 0, "ok_count": 0, "change_count": 1, "bad_count": 0, "error_count": 0, "created": 1741183281}, {"id": 2613778, "st": 1, "ty": 2, "nu": 21, "username": "wx_29792735191823", "userid": 1674602, "pts": [{"p": "sc", "c": ""}, {"p": "sd", "c": ""}, {"p": "rd", "c": ""}, {"p": "rb", "c": ""}, {"p": "qa", "c": ""}, {"p": "pa", "c": ""}, {"p": "oa", "c": ""}, {"p": "na", "c": ""}, {"p": "ma", "c": ""}, {"p": "qb", "c": ""}, {"p": "oa", "c": ""}, {"p": "ra", "c": ""}, {"p": "oc", "c": ""}, {"p": "sb", "c": ""}, {"p": "pb", "c": ""}], "v": 0, "ok_count": 0, "change_count": 1, "bad_count": 0, "error_count": 0, "created": 1743412839}], "ans_count": 19, "andata": {"0": {"subs": [1, 27], "p": 0, "id": 0, "aids": [], "pt": "", "o": 0, "c": 0, "f": 0, "u": 0, "tip": ""}, "1": {"subs": [2, 65], "p": 0, "id": 1, "aids": [4159, 4160, 4161, 163249, 189236, 189237, 419931, 542185, 610806, 688470, 1040652, 1473140], "pt": "sc", "o": 1, "c": 1, "f": 1, "u": 0, "tip": "\u6258\uff0c\u53ea\u6b64\u4e00\u624b\uff01\u5176\u4ed6\u7740\u6cd5\uff0c\u767d\u53efa\u4f4d\u5148\u5c16\u6d3b\u68cb\u3002"}, "2": {"subs": [3], "p": 1, "id": 2, "aids": [4159, 4160, 4161, 163249, 189236, 189237, 419931, 542185, 610806, 688470, 1040652], "pt": "sd", "o": 1, "c": 1, "f": 1, "u": 0, "tip": ""}, "3": {"subs": [4, 14], "p": 2, "id": 3, "aids": [4159, 4160, 4161, 163249, 189236, 189237, 419931, 542185, 610806, 688470, 1040652], "pt": "rd", "o": 1, "c": 1, "f": 1, "u": 0, "tip": ""}, "4": {"subs": [5, 54, 63], "p": 3, "id": 4, "aids": [4159, 419931, 542185, 610806, 688470, 1040652], "pt": "rb", "o": 1, "c": 0, "f": 1, "u": 0, "tip": ""}, "5": {"subs": [6], "p": 4, "id": 5, "aids": [4159, 419931, 542185, 610806], "pt": "qa", "o": 1, "c": 0, "f": 1, "u": 0, "tip": "\u8981\u70b9\uff01"}, "6": {"subs": [7, 41], "p": 5, "id": 6, "aids": [4159, 419931, 542185, 610806], "pt": "pa", "o": 1, "c": 0, "f": 1, "u": 0, "tip": ""}, "7": {"subs": [8, 48], "p": 6, "id": 7, "aids": [4159, 542185, 610806], "pt": "na", "o": 1, "c": 0, "f": 0, "u": 0, "tip": ""}, "8": {"subs": [9, 43], "p": 7, "id": 8, "aids": [4159, 542185], "pt": "qb", "o": 1, "c": 0, "f": 0, "u": 0, "tip": ""}, "9": {"subs": [10], "p": 8, "id": 9, "aids": [4159], "pt": "oa", "o": 1, "c": 0, "f": 0, "u": 0, "tip": ""}, "10": {"subs": [11], "p": 9, "id": 10, "aids": [4159], "pt": "ra", "o": 1, "c": 0, "f": 0, "u": 0, "tip": ""}, "11": {"subs": [12], "p": 10, "id": 11, "aids": [4159], "pt": "oc", "o": 1, "c": 0, "f": 0, "u": 0, "tip": ""}, "12": {"subs": [13], "p": 11, "id": 12, "aids": [4159], "pt": "sb", "o": 1, "c": 0, "f": 0, "u": 0, "tip": "\u4e0d\u6127\u662f\u9ad8\u624b\uff01PF\uff0cPF"}, "13": {"subs": [], "p": 12, "id": 13, "aids": [4159], "pt": "pb", "o": 1, "c": 0, "f": 0, "u": 0, "tip": ""}, "14": {"subs": [15], "p": 3, "id": 14, "aids": [4160, 4161, 163249, 189236, 189237], "pt": "sb", "o": 0, "c": 1, "f": 0, "u": 0, "tip": ""}, "15": {"subs": [16, 22, 35], "p": 14, "id": 15, "aids": [4160, 4161, 163249, 189236, 189237], "pt": "ra", "o": 0, "c": 1, "f": 0, "u": 0, "tip": ""}, "16": {"subs": [17], "p": 15, "id": 16, "aids": [4160, 189236], "pt": "oa", "o": 0, "c": 1, "f": 0, "u": 0, "tip": ""}, "17": {"subs": [18], "p": 16, "id": 17, "aids": [4160, 189236], "pt": "qb", "o": 0, "c": 1, "f": 0, "u": 0, "tip": ""}, "18": {"subs": [19], "p": 17, "id": 18, "aids": [4160, 189236], "pt": "oc", "o": 0, "c": 1, "f": 0, "u": 0, "tip": ""}, "19": {"subs": [20], "p": 18, "id": 19, "aids": [4160, 189236], "pt": "pa", "o": 0, "c": 1, "f": 0, "u": 0, "tip": "\u6b63\u89e32"}, "20": {"subs": [21], "p": 19, "id": 20, "aids": [4160], "pt": "pb", "o": 0, "c": 1, "f": 0, "u": 0, "tip": ""}, "21": {"subs": [], "p": 20, "id": 21, "aids": [4160], "pt": "qa", "o": 0, "c": 1, "f": 0, "u": 0, "tip": "\u767d\u68cb\u88ab\u805a\u6740\uff01"}, "22": {"subs": [23], "p": 15, "id": 22, "aids": [4161], "pt": "qb", "o": 0, "c": 1, "f": 0, "u": 0, "tip": ""}, "23": {"subs": [24], "p": 22, "id": 23, "aids": [4161], "pt": "oc", "o": 0, "c": 1, "f": 0, "u": 0, "tip": ""}, "24": {"subs": [25], "p": 23, "id": 24, "aids": [4161], "pt": "na", "o": 0, "c": 1, "f": 0, "u": 0, "tip": ""}, "25": {"subs": [26], "p": 24, "id": 25, "aids": [4161], "pt": "ma", "o": 0, "c": 1, "f": 0, "u": 0, "tip": ""}, "26": {"subs": [], "p": 25, "id": 26, "aids": [4161], "pt": "pa", "o": 0, "c": 1, "f": 0, "u": 0, "tip": "\u7f13\u6c14\u52ab\uff0c\u5931\u8d25\uff01"}, "27": {"subs": [28], "p": 0, "id": 27, "aids": [4162], "pt": "qb", "o": 0, "c": 0, "f": 1, "u": 0, "tip": "\u4e0d\u662f\u6740\u68cb\u7684\u5730\u65b9"}, "28": {"subs": [29], "p": 27, "id": 28, "aids": [4162], "pt": "sd", "o": 0, "c": 0, "f": 1, "u": 0, "tip": ""}, "29": {"subs": [30], "p": 28, "id": 29, "aids": [4162], "pt": "rd", "o": 0, "c": 0, "f": 1, "u": 0, "tip": ""}, "30": {"subs": [31], "p": 29, "id": 30, "aids": [4162], "pt": "rb", "o": 0, "c": 0, "f": 1, "u": 0, "tip": ""}, "31": {"subs": [32], "p": 30, "id": 31, "aids": [4162], "pt": "ra", "o": 0, "c": 0, "f": 1, "u": 0, "tip": ""}, "32": {"subs": [33], "p": 31, "id": 32, "aids": [4162], "pt": "pa", "o": 0, "c": 0, "f": 1, "u": 0, "tip": ""}, "33": {"subs": [34], "p": 32, "id": 33, "aids": [4162], "pt": "qa", "o": 0, "c": 0, "f": 1, "u": 0, "tip": ""}, "34": {"subs": [], "p": 33, "id": 34, "aids": [4162], "pt": "sc", "o": 0, "c": 0, "f": 1, "u": 0, "tip": "\u767d\u7c98\u662f\u5148\u624b\uff0c\u5df2\u6210\u6d3b\u68cb\u3002\u518d\u8bd5\u8bd5\uff01"}, "35": {"subs": [36], "p": 15, "id": 35, "aids": [163249, 189237], "pt": "pa", "o": 0, "c": 1, "f": 0, "u": 0, "tip": ""}, "36": {"subs": [37, 39], "p": 35, "id": 36, "aids": [163249, 189237], "pt": "oc", "o": 0, "c": 1, "f": 0, "u": 0, "tip": ""}, "37": {"subs": [38], "p": 36, "id": 37, "aids": [163249], "pt": "qb", "o": 0, "c": 1, "f": 0, "u": 0, "tip": ""}, "38": {"subs": [], "p": 37, "id": 38, "aids": [163249], "pt": "na", "o": 0, "c": 1, "f": 0, "u": 0, "tip": "\u6b63\u89e33"}, "39": {"subs": [40], "p": 36, "id": 39, "aids": [189237], "pt": "na", "o": 0, "c": 1, "f": 0, "u": 0, "tip": ""}, "40": {"subs": [], "p": 39, "id": 40, "aids": [189237], "pt": "qb", "o": 0, "c": 1, "f": 0, "u": 0, "tip": "\u6b63\u89e34"}, "41": {"subs": [42], "p": 6, "id": 41, "aids": [419931], "pt": "oc", "o": 0, "c": 0, "f": 1, "u": 0, "tip": ""}, "42": {"subs": [], "p": 41, "id": 42, "aids": [419931], "pt": "ra", "o": 0, "c": 0, "f": 1, "u": 0, "tip": ""}, "43": {"subs": [44], "p": 8, "id": 43, "aids": [542185], "pt": "oc", "o": 1, "c": 0, "f": 0, "u": 0, "tip": ""}, "44": {"subs": [45], "p": 43, "id": 44, "aids": [542185], "pt": "ra", "o": 1, "c": 0, "f": 0, "u": 0, "tip": ""}, "45": {"subs": [46], "p": 44, "id": 45, "aids": [542185], "pt": "oa", "o": 1, "c": 0, "f": 0, "u": 0, "tip": ""}, "46": {"subs": [47], "p": 45, "id": 46, "aids": [542185], "pt": "sb", "o": 1, "c": 0, "f": 0, "u": 0, "tip": ""}, "47": {"subs": [], "p": 46, "id": 47, "aids": [542185], "pt": "pb", "o": 1, "c": 0, "f": 0, "u": 0, "tip": ""}, "48": {"subs": [49], "p": 7, "id": 48, "aids": [610806], "pt": "ra", "o": 1, "c": 0, "f": 0, "u": 0, "tip": ""}, "49": {"subs": [50], "p": 48, "id": 49, "aids": [610806], "pt": "oa", "o": 1, "c": 0, "f": 0, "u": 0, "tip": ""}, "50": {"subs": [51], "p": 49, "id": 50, "aids": [610806], "pt": "qb", "o": 1, "c": 0, "f": 0, "u": 0, "tip": ""}, "51": {"subs": [52], "p": 50, "id": 51, "aids": [610806], "pt": "oc", "o": 1, "c": 0, "f": 0, "u": 0, "tip": ""}, "52": {"subs": [53], "p": 51, "id": 52, "aids": [610806], "pt": "sb", "o": 1, "c": 0, "f": 0, "u": 0, "tip": ""}, "53": {"subs": [], "p": 52, "id": 53, "aids": [610806], "pt": "pb", "o": 1, "c": 0, "f": 0, "u": 0, "tip": ""}, "54": {"subs": [55], "p": 4, "id": 54, "aids": [688470], "pt": "oa", "o": 0, "c": 0, "f": 1, "u": 0, "tip": ""}, "55": {"subs": [56], "p": 54, "id": 55, "aids": [688470], "pt": "pa", "o": 0, "c": 0, "f": 1, "u": 0, "tip": ""}, "56": {"subs": [57], "p": 55, "id": 56, "aids": [688470], "pt": "qa", "o": 0, "c": 0, "f": 1, "u": 0, "tip": ""}, "57": {"subs": [58], "p": 56, "id": 57, "aids": [688470], "pt": "na", "o": 0, "c": 0, "f": 1, "u": 0, "tip": ""}, "58": {"subs": [59], "p": 57, "id": 58, "aids": [688470], "pt": "ma", "o": 0, "c": 0, "f": 1, "u": 0, "tip": ""}, "59": {"subs": [60], "p": 58, "id": 59, "aids": [688470], "pt": "ra", "o": 0, "c": 0, "f": 1, "u": 0, "tip": ""}, "60": {"subs": [61], "p": 59, "id": 60, "aids": [688470], "pt": "oa", "o": 0, "c": 0, "f": 1, "u": 0, "tip": ""}, "61": {"subs": [62], "p": 60, "id": 61, "aids": [688470], "pt": "qb", "o": 0, "c": 0, "f": 1, "u": 0, "tip": ""}, "62": {"subs": [], "p": 61, "id": 62, "aids": [688470], "pt": "oc", "o": 0, "c": 0, "f": 1, "u": 0, "tip": "\u4e24\u624b\u52ab\uff0c\u5931\u8d25"}, "63": {"subs": [64], "p": 4, "id": 63, "aids": [1040652], "pt": "pa", "o": 0, "c": 0, "f": 1, "u": 0, "tip": ""}, "64": {"subs": [], "p": 63, "id": 64, "aids": [1040652], "pt": "qa", "o": 0, "c": 0, "f": 1, "u": 0, "tip": ""}, "65": {"subs": [66], "p": 1, "id": 65, "aids": [1473140], "pt": "sb", "o": 0, "c": 1, "f": 0, "u": 0, "tip": ""}, "66": {"subs": [67], "p": 65, "id": 66, "aids": [1473140], "pt": "ra", "o": 0, "c": 1, "f": 0, "u": 0, "tip": ""}, "67": {"subs": [68], "p": 66, "id": 67, "aids": [1473140], "pt": "qb", "o": 0, "c": 1, "f": 0, "u": 0, "tip": ""}, "68": {"subs": [69], "p": 67, "id": 68, "aids": [1473140], "pt": "oc", "o": 0, "c": 1, "f": 0, "u": 0, "tip": ""}, "69": {"subs": [70], "p": 68, "id": 69, "aids": [1473140], "pt": "pa", "o": 0, "c": 1, "f": 0, "u": 0, "tip": ""}, "70": {"subs": [], "p": 69, "id": 70, "aids": [1473140], "pt": "na", "o": 0, "c": 1, "f": 0, "u": 0, "tip": ""}}, "disuse": 2, "sx": 10, "sy": 12, "pos_x1": 9, "pos_x2": 18, "pos_y1": 0, "pos_y2": 11, "ineb": false, "extendwidth": 0, "signs": [], "luozis": [], "isguess": false, "objtype": "timu", "ru": 2, "content": "amsTXVERHRATQVYRHRATQlcRHRATXlERHRATXFURHRATXFcRHRATXVcRHRATQFURHRATQlYRbBwRaBFDUhIdExFBUhIdExFBVxIdExFBVhIdExFCUhIdExFCWRIdExFcUxJsbg==", "ok_answers": "amsTQFARHRATQFcRHRATQVcRHRATQVERHRATQlIRHRATQ1IRHRATXVIRHRATQlERHRATXFIRHRATQVIRHRATXFARHRATQFERHRATQ1ERbBwRaBFAUhIdExFAVRIdExFBVRIdExFBUxIdExFCUBIdExFDUBIdExFdUBIdExFCUxIdExFcUhIdExFBUBIdExFcUBIdExFAUxIdExFDUxJsHxNoE0NSER8TE0NVER8TE0JVER8TE0JTER8TE0FQER8TE0BQER8TE15QER8TE0JQER8TE19QER8TE0FTER8TE19SER8TE0NTER8TE0BTEW5u", "change_answers": "amsTQFARHRATQFcRHRATQVcRHRATQFERHRATQVIRHRATXFIRHRATQlERHRATXFARHRATQ1IRHRATQ1ERHRATQlIRbBwRaBFAUhIdExFAVRIdExFBVRIdExFAUxIdExFBUBIdExFCUxIdExFcUhIdExFdUBIdExFeUBIdExFDUBJsHxNoE0NSER8TE0NVER8TE0JVER8TE0NTER8TE0JQER8TE0BQER8TE19SER8TE0FTER8TE15QEW4fEWsTQFARHRATQFcRHRATQVcRHRATQFERHRATQVIRHRATXFIRHRATQlERHRATXFARHRATQ1IRbBwRaBFAUhIdExFAVRIdExFBVRIdExFAUxIdExFBUBIdExFDUBIdExFcUhIdExFdUBIdExFCUxJsHxNoE0NSER8TE0NTER8TE0JQER8TE0FTER8TE19SER8TE0BQER8TE15QEW5u", "fail_answers": "amsTQlERHRATQFcRHRATQVcRHRATQVERHRATQVIRHRATQ1IRHRATQlIRHRATQFARbBwRaBFAUhIdExFAVRIdExFBVRIdExFBUxIdExFCUBIdExFDUBIdExFcUhIdExFBUBJsHxNoE0NSER8TE0NVER8TE0JVER8TE0JTER8TE19QER8TE0BQER8TE0FQER8TE15QER8TE11QER8TE0JQER8TE19QER8TE0FTER8TE19SEW4fEWsTQFARHRATQFcRHRATQVcRHRATQVERHRATQ1IRHRATQlIRbG0=", "level": 462, "desc": "\u85e4\u6cfd\u79c0\u884c\u4e5d\u6bb5\u521b\u4f5c", "yes_count": 966, "no_count": 1517, "pos": [], "attrtype": 0, "showrettip": false, "is_public": true, "inerror": false, "qshids": [], "myan": {}, "hasbook": false, "hasspec": false, "myoper": {"mystar": false, "mytags": [], "tags": []}, "candisuseall": false, "userlevel": 0, "clicktime": 0, "xz": 0, "comments": [{"id": 211417, "dou": 0, "doustatus": 0, "douname": "", "username": "QQde\u5bc6\u7801", "userid": 4323, "headpath": "headicon_128.jpg", "updated": 1501570997, "showcontent": "\u89e3\u7b543\u4f3c\u4e4e\u662f\u9ed1\u6709\u5229\u7684\u7f13\u6c14\u52ab\uff1f\u5982\u679c\u662f\u7684\u8bdd\u5e94\u8be5\u653e\u5165\u53d8\u5316\u7b54\u6848......"}, {"id": 236464, "dou": 0, "doustatus": 0, "douname": "", "username": "\u6c5f\u6c49\u601d\u5f52\u5ba2", "userid": 6563, "headpath": "headicon_128.jpg", "updated": 1509323254, "showcontent": "9\u5148\u8d7011\u4e0d\u4e00\u6837\u5417"}, {"id": 423124, "dou": 0, "doustatus": 0, "douname": "", "username": "\u68a6\u4e5d\u9633\u5149", "userid": 169993, "headpath": "head/2019/9/14/169993_64024_39_30.png", "updated": 1553763576, "showcontent": "\u62111\u6b21\u505a\u5bf9"}, {"id": 474676, "dou": 0, "doustatus": 0, "douname": "", "username": "\u90d1\u5584\u89c9", "userid": 79568, "headpath": "head/2022/4/30/79568_67260_14_36.png", "updated": 1564453669, "showcontent": "\u7b80\u5355"}, {"id": 511935, "dou": 0, "doustatus": 0, "douname": "", "username": "\u7231\u4e50\u5955", "userid": 2768, "headpath": "headicon_128.jpg", "updated": 1570291095, "showcontent": "<a href=\"/q/37321/\" target=\"_blank\">Q-37321</a>"}, {"id": 547017, "dou": 0, "doustatus": 0, "douname": "", "username": "\u5468\u777f\u5b87", "userid": 550009, "headpath": "headicon_128.jpg", "updated": 1578738474, "showcontent": "\u79d2\u6740"}, {"id": 912718, "dou": 0, "doustatus": 0, "douname": "", "username": "\u77f3\u77e5\u606918", "userid": 107445, "headpath": "head/2022/4/29/107445_37291_38_20.png", "updated": 1603511592, "showcontent": "\u9898\u662f\u86ee\u96be\u7684\uff0c\u4e0d\u8fc7\u7b54\u6848\u8fd8\u662f\u597d\u8bb0\u7684"}, {"id": 1105872, "dou": 0, "doustatus": 0, "douname": "", "username": "\u674e\u7855\u6f8419", "userid": 553745, "headpath": "head/2022/8/22/553745_65151_0_34.png", "updated": 1634390423, "showcontent": "\u201c\u86ee\u96be\u7684\u201d"}, {"id": 1225269, "dou": 0, "doustatus": 0, "douname": "", "username": "\u8d3a\u94b0\u5586", "userid": 329034, "headpath": "headicon_128.jpg", "updated": 1651734064, "showcontent": "\u6bd4\u8f83\u7b80\u5355"}, {"id": 1271353, "dou": 0, "doustatus": 0, "douname": "", "username": "\u767e\u6bb5\u8d75\u5929\u6b63", "userid": 1334858, "headpath": "headicon_128.jpg", "updated": 1656597091, "showcontent": "\u3002\u3002\u3002"}, {"id": 1324238, "dou": 0, "doustatus": 0, "douname": "", "username": "\u5eb7\u6893\u946b", "userid": 1191154, "headpath": "userhead/14.jpg", "updated": 1660898489, "showcontent": "\u6211\u4e00\u6b21\u505a\u5bf9"}, {"id": 1487245, "dou": 0, "doustatus": 0, "douname": "", "username": "\u66ae\u96ea\u82b3\u7eef", "userid": 1404249, "headpath": "head/2023/1/27/1404249_89912_10_26.png", "updated": 1676545452, "showcontent": "\u540e\u9762\u4e5f\u6709\u70b9\u610f\u601d"}, {"id": 1666951, "dou": 0, "doustatus": 0, "douname": "", "username": "\u674e\u946b22", "userid": 1512040, "headpath": "head/2025/4/2/1512040_14991_4_23.png", "updated": 1700216335, "showcontent": "\u672c\u9898\u6b63\u786e\uff0c\u4f46\u8d85\u65f6\u672a\u901a\u8fc7"}, {"id": 1771455, "dou": 0, "doustatus": 0, "douname": "", "username": "skyler_1129", "userid": 686262, "headpath": "head/2023/10/16/686262_12044_44_40.png", "updated": 1712288425, "showcontent": "PF\u662f\u4ec0\u9ebc\u610f\u601d?"}, {"id": 1941603, "dou": 0, "doustatus": 0, "douname": "", "username": "\u9b4f\u94ed\u6cfd", "userid": 1494711, "headpath": "headicon_128.jpg", "updated": 1729215556, "showcontent": "PF\u5c31\u662fPF"}, {"id": 1941604, "dou": 0, "doustatus": 0, "douname": "", "username": "\u9b4f\u94ed\u6cfd", "userid": 1494711, "headpath": "headicon_128.jpg", "updated": 1729215598, "showcontent": "PF\u662f\u4f69\u670d"}]}
